pretty_markdown_tables/__init__.py
pretty_markdown_tables/tables.py
pretty_markdown_tables-0.1.3.dist-info/WHEEL
pretty_markdown_tables-0.1.3.dist-info/METADATA
pretty_markdown_tables-0.1.3.dist-info/RECORD
