Metadata-Version: 2.1
Name: pretty-markdown-tables
Version: 0.1.3
Summary: 
Author: vidigalp
Author-email: vidigal.pedro@gmail.com
Requires-Python: >=3.8,<4.0
Classifier: Programming Language :: Python :: 3
Classifier: Programming Language :: Python :: 3.8
Classifier: Programming Language :: Python :: 3.9
Classifier: Programming Language :: Python :: 3.10
Classifier: Programming Language :: Python :: 3.11
Requires-Dist: loguru (>=0.6.0,<0.7.0)
Requires-Dist: markdown2 (>=2.4.7,<3.0.0)
Requires-Dist: pandas (>=1.5.3,<2.0.0)
Requires-Dist: pretty-html-table (>=0.9.16,<0.10.0)
Requires-Dist: pytest (>=7.2.1,<8.0.0)
